django_admin_collaborator/__init__.py
django_admin_collaborator/apps.py
django_admin_collaborator/consumers.py
django_admin_collaborator/defaults.py
django_admin_collaborator/routing.py
django_admin_collaborator/utils.py
django_admin_collaborator/static/django_admin_collaborator/css/admin_chat.css
django_admin_collaborator/static/django_admin_collaborator/js/admin_chat.js
django_admin_collaborator/static/django_admin_collaborator/js/admin_edit.js
django_admin_collaborator-0.4.4.dist-info/licenses/LICENSE
django_admin_collaborator-0.4.4.dist-info/METADATA
django_admin_collaborator-0.4.4.dist-info/WHEEL
django_admin_collaborator-0.4.4.dist-info/top_level.txt
django_admin_collaborator-0.4.4.dist-info/RECORD
